solo/__init__.py
solo/adabelief.py
solo/adafactor.py
solo/adam.py
solo/adamw.py
solo/base.py
solo/quantizer/__init__.py
solo/quantizer/bf16.py
solo/quantizer/de_2bit.py
solo/quantizer/de_3bit.py
solo/quantizer/de_4bit.py
solo/quantizer/de_8bit.py
solo/quantizer/de_sr_2bit.py
solo/quantizer/de_sr_3bit.py
solo/quantizer/de_sr_4bit.py
solo/quantizer/de_sr_8bit.py
solo/quantizer/linear_2bit.py
solo/quantizer/linear_3bit.py
solo/quantizer/linear_4bit.py
solo/quantizer/linear_8bit.py
solo/quantizer/linear_sr_2bit.py
solo/quantizer/linear_sr_3bit.py
solo/quantizer/linear_sr_4bit.py
solo/quantizer/linear_sr_8bit.py
solo/quantizer/qema_2bit.py
solo/quantizer/qema_3bit.py
solo/quantizer/qema_4bit.py
solo/quantizer/qema_8bit.py
solo/quantizer/subclass_2bit.py
solo/quantizer/subclass_3bit.py
solo/quantizer/subclass_4bit.py
solo/quantizer/subclass_8bit.py
solo/quantizer/utils.py
solow-0.1.5.dist-info/LICENSE
solow-0.1.5.dist-info/METADATA
solow-0.1.5.dist-info/WHEEL
solow-0.1.5.dist-info/top_level.txt
solow-0.1.5.dist-info/RECORD
